{
    "MPEL": {
        "SC_0": [
            {
                "EMI_0": 999999,
                "EMI_xdbru": 999999
            }
        ],
        "SC_ayjl6": [
            {
                "EMI_0": null,
                "EMI_xdbru": null
            }
        ],
        "SC_p6iyw": [
            {
                "EMI_0": null,
                "EMI_xdbru": null
            }
        ]
    },
    "MPEE": {
        "SC_0": [
            {
                "EMI_0": 0,
                "EMI_xdbru": 0
            }
        ],
        "SC_ayjl6": [
            {
                "EMI_0": null,
                "EMI_xdbru": null
            }
        ],
        "SC_p6iyw": [
            {
                "EMI_0": null,
                "EMI_xdbru": null
            }
        ]
    }
}